<?xml version="1.0" encoding="UTF-8"?>
<annotation>
  <filename>dining_out_public_roads_avenue_multiplex_train_p_day_202020304_18537.jpg</filename>
  <size>
    <width>1920</width>
    <height>1080</height>
    <depth>3</depth>
  </size>
  <object>
    <name>chair</name>
    <bndbox>
      <xmin>32</xmin>
      <ymin>322</ymin>
      <xmax>65</xmax>
      <ymax>363</ymax>
    </bndbox>
  </object>
  <object>
    <name>table_chair</name>
    <bndbox>
      <xmin>1</xmin>
      <ymin>297</ymin>
      <xmax>66</xmax>
      <ymax>364</ymax>
    </bndbox>
  </object>
  <object>
    <name>table</name>
    <bndbox>
      <xmin>236</xmin>
      <ymin>300</ymin>
      <xmax>298</xmax>
      <ymax>340</ymax>
    </bndbox>
  </object>
  <object>
    <name>table</name>
    <bndbox>
      <xmin>146</xmin>
      <ymin>275</ymin>
      <xmax>207</xmax>
      <ymax>313</ymax>
    </bndbox>
  </object>
  <object>
    <name>table</name>
    <bndbox>
      <xmin>1</xmin>
      <ymin>298</ymin>
      <xmax>34</xmax>
      <ymax>362</ymax>
    </bndbox>
  </object>
</annotation>
